neuralx/__init__.py
neuralx/confusion_matrix.py
neuralx/function_utils.py
neuralx/neural_network.py
neuralx-1.0.6.dist-info/METADATA
neuralx-1.0.6.dist-info/WHEEL
neuralx-1.0.6.dist-info/licenses/LICENSE
neuralx-1.0.6.dist-info/RECORD
