Metadata-Version: 2.1
Name: neuralx
Version: 1.0.6
Summary: a user-friendly Python package for neural networks.
Project-URL: Homepage, https://github.com/mehdimhb/NeuralX
Project-URL: Bug Tracker, https://github.com/mehdimhb/NeuralX/issues
Author-email: Mehdi Mohebbi <mehdi.mhb3@gmail.com>
License-File: LICENSE
Classifier: License :: OSI Approved :: MIT License
Classifier: Operating System :: OS Independent
Classifier: Programming Language :: Python :: 3
Requires-Python: >=3.11
